MANIFEST.in
README.rst
bootstrap.py
buildout.cfg
jpl.plone2ldap.sublime-project
setup.py
docs/HISTORY.txt
docs/INSTALL.txt
docs/LICENSE.txt
src/jpl/__init__.py
src/jpl.plone2ldap.egg-info/PKG-INFO
src/jpl.plone2ldap.egg-info/SOURCES.txt
src/jpl.plone2ldap.egg-info/dependency_links.txt
src/jpl.plone2ldap.egg-info/namespace_packages.txt
src/jpl.plone2ldap.egg-info/not-zip-safe
src/jpl.plone2ldap.egg-info/requires.txt
src/jpl.plone2ldap.egg-info/top_level.txt
src/jpl/plone2ldap/__init__.py
src/jpl/plone2ldap/main.py
src/jpl/plone2ldap/tests/__init__.py