Metadata-Version: 1.1
Name: jpl.plone2ldap
Version: 0.0.0
Summary: Export Plone usernames and passwords and import them into an LDAP server
Home-page: https://github.com/MCLConsortium/jpl.plone2ldap
Author: Sean Kelly
Author-email: sean.kelly@jpl.nasa.gov
License: ALv2
Download-URL: https://github.com/MCLConsortium/jpl.plone2ldap/archive/0.0.0.zip
Keywords: plone zope ldap username password export import
Platform: UNKNOWN
Classifier: Development Status :: 2 - Pre-Alpha
Classifier: Environment :: Web Environment
Classifier: Framework :: Plone
Classifier: License :: Other/Proprietary License
Classifier: Operating System :: OS Independent
Classifier: Programming Language :: Python
Classifier: Topic :: Software Development :: Libraries :: Python Modules
Classifier: Topic :: System :: Systems Administration :: Authentication/Directory :: LDAP
